bd_sig_filter/BOMClass.py
bd_sig_filter/ComponentClass.py
bd_sig_filter/ComponentListClass.py
bd_sig_filter/SigEntryClass.py
bd_sig_filter/__init__.py
bd_sig_filter/bd_data.py
bd_sig_filter/bd_project.py
bd_sig_filter/config.py
bd_sig_filter/global_values.py
bd_sig_filter/main.py
bd_sig_filter-1.8.dist-info/LICENSE
bd_sig_filter-1.8.dist-info/METADATA
bd_sig_filter-1.8.dist-info/WHEEL
bd_sig_filter-1.8.dist-info/entry_points.txt
bd_sig_filter-1.8.dist-info/top_level.txt
bd_sig_filter-1.8.dist-info/RECORD
