Metadata-Version: 2.1
Name: bd_sig_filter
Version: 1.8
Summary: BD_sig_filter - BD Script to ignore components matched from Signature scan likely to be partial or invalid matches.
Author-email: Matthew Brady <mbrad@blackduck.com>
Project-URL: Homepage, https://github.com/matthewb66/bd_sig_filter
Project-URL: Issues, https://github.com/matthewb66/bd_sig_filter/issues
Classifier: Programming Language :: Python :: 3
Classifier: License :: OSI Approved :: MIT License
Classifier: Operating System :: OS Independent
Requires-Python: >=3.8
License-File: LICENSE
Requires-Dist: blackduck >1.0.3
Requires-Dist: tabulate
Requires-Dist: thefuzz
